synaptik_core/__init__.py
synaptik_core/synaptik_core.abi3.so
synaptik_core_beta-0.1.6.dist-info/METADATA
synaptik_core_beta-0.1.6.dist-info/WHEEL
synaptik_core_beta-0.1.6.dist-info/RECORD
