Metadata-Version: 2.4
Name: synaptik-core-beta
Version: 0.1.6
Classifier: Programming Language :: Python
Classifier: Programming Language :: Rust
Classifier: Programming Language :: Python :: Implementation :: CPython
Summary: Synaptik Core Python bindings (hackathon build)
Author: Janay Harris
License: Apache-2.0
Requires-Python: >=3.8
